p03py/__init__.py
p03py/interface_p03.py
p03py/Exemplos/__init__.py
p03py/Exemplos/diagnostico.py
p03py/Exemplos/teste_leitura_serial.py
p03py/Exemplos/teste_leitura_tcp.py
p03py-1.0.4.dist-info/licenses/LICENSE
p03py-1.0.4.dist-info/METADATA
p03py-1.0.4.dist-info/WHEEL
p03py-1.0.4.dist-info/top_level.txt
p03py-1.0.4.dist-info/RECORD
