Metadata-Version: 2.4
Name: p03py
Version: 1.0.4
Summary: Python library for reading industrial scales using the P03 protocol.
Home-page: https://github.com/roneitop/p03py
Author: Ronei Toporcov
Author-email: toporcov@hotmail.com
License: MIT
Classifier: Programming Language :: Python :: 3
Classifier: License :: OSI Approved :: MIT License
Classifier: Operating System :: OS Independent
Requires-Python: >=3.7
License-File: LICENSE
Dynamic: author
Dynamic: author-email
Dynamic: classifier
Dynamic: description
Dynamic: description-content-type
Dynamic: home-page
Dynamic: license
Dynamic: license-file
Dynamic: requires-python
Dynamic: summary
